numiner/__init__.py
numiner/__main__.py
numiner/classes/__init__.py
numiner/classes/converter.py
numiner/classes/letter.py
numiner/classes/sheet.py
numiner-0.2.1.dist-info/entry_points.txt
numiner-0.2.1.dist-info/LICENSE
numiner-0.2.1.dist-info/WHEEL
numiner-0.2.1.dist-info/METADATA
numiner-0.2.1.dist-info/RECORD
