Metadata-Version: 2.1
Name: numiner
Version: 0.2.1
Summary: NUM Miner (Tool to create open dataset for Handwritten Text Recognition)
Home-page: https://github.com/khasbilegt/numiner/
License: MIT
Keywords: htr,hwr,data,dataset,image,tool
Author: Khasbilegt.TS
Author-email: khasbilegt.ts@gmail.com
Requires-Python: >=3.8,<4.0
Classifier: License :: OSI Approved :: MIT License
Classifier: Programming Language :: Python :: 3
Classifier: Programming Language :: Python :: 3.8
Requires-Dist: coveralls (>=2.0.0,<3.0.0)
Requires-Dist: matplotlib (>=3.2.1,<4.0.0)
Requires-Dist: opencv-python (>=4.2.0,<5.0.0)
Requires-Dist: pandas (>=1.0.3,<2.0.0)
Requires-Dist: toml (>=0.10.0,<0.11.0)
Project-URL: Repository, https://github.com/khasbilegt/numiner/
